igimf/__init__.py
igimf/classes.py
igimf/downsizing.py
igimf/plots.py
igimf/utilities.py
igimf-1.0.0.dist-info/licenses/LICENSE
igimf-1.0.0.dist-info/METADATA
igimf-1.0.0.dist-info/WHEEL
igimf-1.0.0.dist-info/top_level.txt
igimf-1.0.0.dist-info/RECORD
