Metadata-Version: 2.4
Name: igimf
Version: 1.0.0
Summary: IGIMF models, plots, and utilities
Author: Eda Gjergo
License-Expression: GPL-3.0-only
Project-URL: Homepage, https://github.com/edagjergo/pyIGIMF
Project-URL: Issues, https://github.com/edagjergo/pyIGIMF/issues
Classifier: Programming Language :: Python :: 3
Classifier: Operating System :: OS Independent
Classifier: Intended Audience :: Science/Research
Classifier: Topic :: Scientific/Engineering :: Astronomy
Requires-Python: >=3.9
License-File: LICENSE
Requires-Dist: numpy>=1.26.4
Requires-Dist: scipy>=1.14.1
Requires-Dist: pandas>=2.2.3
Requires-Dist: matplotlib>=3.9.2
Requires-Dist: scikit-learn>=1.5.1
Requires-Dist: colorcet>=3.1.0
Requires-Dist: dill>=0.3.9
Requires-Dist: astropy>=6.0.0
Requires-Dist: plotly>=6.0.1
Dynamic: license-file
